{
  "name": "Swole Apes #8551",
  "description": "8,888 Swole Apes have lifted themselves up and risen to fend off the oncoming goblin hordes. The Bored Ape masses have proven themselves physically incapable. These elite apes, however, have proven and forged themselves, both physically and mentally, amongst the trials and tribulations of the iron temple. Thus, the Swole Ape Fitness Club was conceived.",
  "image": "ipfs://bafybeicxuczsimn6yuqky5omlll3jz33vkitiqrytipy3ljjaxknjq4bse",
  "attributes": "",
  "dna": "2bfe7cde3dde8c9beed8e944ee2a71e1ce549557",
  "edition": 8551,
  "external_url": "https://swoleapefitness.club",
  "date": 1655885343232,
  "compiler": "HashLips Art Engine - codeSTACKr Modified"
}